petrichor_script_lexer/__init__.py
petrichor_script_lexer/petrichorscriptlexer.py
petrichor_script_lexer-1.0.2.dist-info/METADATA
petrichor_script_lexer-1.0.2.dist-info/WHEEL
petrichor_script_lexer-1.0.2.dist-info/entry_points.txt
petrichor_script_lexer-1.0.2.dist-info/licenses/LICENSE
petrichor_script_lexer-1.0.2.dist-info/RECORD
