Metadata-Version: 2.3
Name: petrichor-script-lexer
Version: 1.0.2
Summary: A custom RegexLexer for Petrichor Script.
Project-URL: Repository, https://github.com/sparklitwizzl/petrichor
Project-URL: Issues, https://github.com/sparklitwizzl/petrichor/issues
Author-email: SparkliTwizzl <github@sparklitwizzl.com>
License: Petrichor Script Lexer
License-File: LICENSE
Classifier: License :: Free To Use But Restricted
Classifier: Operating System :: OS Independent
Classifier: Programming Language :: Python :: 3
Requires-Python: >=3.12
Requires-Dist: pygments
